runner/__init__.py
runner/common/common.py
runner/common/common_test.py
runner/exceptions.py
runner/exit/__init__.py
runner/exit/exceptions.py
runner/exit/exit_runner.py
runner/exit/exit_runner_test.py
runner/exit/helpers.py
runner/exit/helpers_test.py
runner/exit/subscriber.py
runner/exit/subscriber_test.py
runner/runner.py
runner/runner_test.py
runner/task/__init__.py
runner/task/exceptions.py
runner/task/helpers.py
runner/task/helpers_test.py
runner/task/subscriber.py
runner/task/subscriber_test.py
runner/task/task_runner.py
runner/task/task_runner_test.py
runner/trigger/__init__.py
runner/trigger/exceptions.py
runner/trigger/helpers.py
runner/trigger/helpers_test.py
runner/trigger/subscriber.py
runner/trigger/subscriber_test.py
runner/trigger/trigger_runner.py
runner/trigger/trigger_runner_test.py
sdk/__init__.py
sdk/auth/__init__.py
sdk/auth/authentication.py
sdk/auth/exceptions.py
sdk/centralized_config/__init__.py
sdk/centralized_config/centralized_config.py
sdk/centralized_config/centralized_config_test.py
sdk/centralized_config/exceptions.py
sdk/ephemeral_storage/__init__.py
sdk/ephemeral_storage/ephemeral_storage.py
sdk/ephemeral_storage/ephemeral_storage_test.py
sdk/ephemeral_storage/exceptions.py
sdk/kai_nats_msg_pb2.py
sdk/kai_nats_msg_pb2.pyi
sdk/kai_sdk.py
sdk/kai_sdk_test.py
sdk/measurements/__init__.py
sdk/measurements/exceptions.py
sdk/measurements/measurements.py
sdk/measurements/measurements_test.py
sdk/messaging/__init__.py
sdk/messaging/exceptions.py
sdk/messaging/messaging.py
sdk/messaging/messaging_test.py
sdk/messaging/messaging_utils.py
sdk/messaging/messaging_utils_test.py
sdk/metadata/__init__.py
sdk/metadata/metadata.py
sdk/metadata/metadata_test.py
sdk/model_registry/__init__.py
sdk/model_registry/exceptions.py
sdk/model_registry/model_registry.py
sdk/model_registry/model_registry_test.py
sdk/persistent_storage/__init__.py
sdk/persistent_storage/exceptions.py
sdk/persistent_storage/persistent_storage.py
aio_runner_example-1.5.0.dist-info/METADATA
aio_runner_example-1.5.0.dist-info/WHEEL
aio_runner_example-1.5.0.dist-info/RECORD
