Metadata-Version: 2.1
Name: aio-runner-example
Version: 1.5.0
Summary: AIO SDK's implementation in Python
Keywords: python,runner,aio
Author: Intelygenz - AIO Team
Maintainer: Intelygenz - AIO Team
Requires-Python: >=3.11,<3.12
Classifier: Programming Language :: Python :: 3
Classifier: Programming Language :: Python :: 3.11
Requires-Dist: grpcio (==1.59.3)
Requires-Dist: loguru (==0.7.0)
Requires-Dist: minio (==7.2.0)
Requires-Dist: nats-py (==2.6.0)
Requires-Dist: opentelemetry-exporter-otlp-proto-grpc (==1.23.0)
Requires-Dist: opentelemetry-sdk (==1.23.0)
Requires-Dist: protobuf (>=4.23.0,<=4.23.4)
Requires-Dist: python-keycloak (==3.7.0)
Requires-Dist: redis[hiredis] (==5.0.1)
Requires-Dist: semver (==3.0.2)
Requires-Dist: vyper-config (==1.1.1)
